{
    "criteria": {
        "has_items": {
            "trigger": "minecraft:inventory_changed",
            "conditions": {
                "items": [
                    {
                        "tag": "minecraft:small_flowers"
                    },
                    {
                        "tag": "minecraft:leaves"
                    },
                    {
                      "items": ["minecraft:dirt"]
                    }
                ]
            }
        },
        "has_result": {
          "trigger": "minecraft:inventory_changed",
          "conditions": {
              "items": [
                  {
                    "items": ["minecraft:moss_block"]
                  }
              ]
          }
      }
    },
    "requirements": [
      ["has_items", "has_result"]
    ],
    "rewards": {
        "recipes": [
            "mcr:crafting/moss_block"
        ]
    },
    "parent": "mcr:root"
}