{
    "criteria": {
        "has_items": {
            "trigger": "minecraft:inventory_changed",
            "conditions": {
                "items": [
                    {
                      "tems": ["minecraft:glass"]
                    },
                    {
                      "items": ["minecraft:soul_lantern"]
                    }
                ]
            }
        }
    },
    "rewards": {
        "recipes": [
            "mcr:crafting/sea_lantern"
        ]
    },
    "parent": "mcr:root"
}